{
  "schema_version": "v2",
  "reciter_slug": "qcom_mishari_alafasy",
  "surah": 96,
  "ayahs": [
    {
      "surah": 96,
      "ayah": 1,
      "start_s": 0.04800000000000001,
      "end_s": 3.9635,
      "source": "aligned"
    },
    {
      "surah": 96,
      "ayah": 2,
      "start_s": 4.3955,
      "end_s": 8.521,
      "source": "aligned"
    },
    {
      "surah": 96,
      "ayah": 3,
      "start_s": 8.785499999999999,
      "end_s": 11.943,
      "source": "aligned"
    },
    {
      "surah": 96,
      "ayah": 4,
      "start_s": 12.269499999999999,
      "end_s": 15.019000000000002,
      "source": "aligned"
    },
    {
      "surah": 96,
      "ayah": 5,
      "start_s": 15.2975,
      "end_s": 19.704,
      "source": "aligned"
    },
    {
      "surah": 96,
      "ayah": 6,
      "start_s": 20.4045,
      "end_s": 27.262999999999998,
      "source": "aligned"
    },
    {
      "surah": 96,
      "ayah": 7,
      "start_s": 27.7765,
      "end_s": 30.144000000000002,
      "source": "aligned"
    },
    {
      "surah": 96,
      "ayah": 8,
      "start_s": 30.494500000000002,
      "end_s": 34.260000000000005,
      "source": "aligned"
    },
    {
      "surah": 96,
      "ayah": 9,
      "start_s": 34.7975,
      "end_s": 37.606,
      "source": "aligned"
    },
    {
      "surah": 96,
      "ayah": 10,
      "start_s": 38.1855,
      "end_s": 40.614999999999995,
      "source": "aligned"
    },
    {
      "surah": 96,
      "ayah": 11,
      "start_s": 41.0585,
      "end_s": 44.977000000000004,
      "source": "aligned"
    },
    {
      "surah": 96,
      "ayah": 12,
      "start_s": 45.5565,
      "end_s": 47.913000000000004,
      "source": "aligned"
    },
    {
      "surah": 96,
      "ayah": 13,
      "start_s": 48.4465,
      "end_s": 52.559000000000005,
      "source": "aligned"
    },
    {
      "surah": 96,
      "ayah": 14,
      "start_s": 53.09349999999999,
      "end_s": 58.391000000000005,
      "source": "aligned"
    },
    {
      "surah": 96,
      "ayah": 15,
      "start_s": 58.917500000000004,
      "end_s": 67.366,
      "source": "aligned"
    },
    {
      "surah": 96,
      "ayah": 16,
      "start_s": 67.6135,
      "end_s": 72.06800000000001,
      "source": "aligned"
    },
    {
      "surah": 96,
      "ayah": 17,
      "start_s": 72.2535,
      "end_s": 74.607,
      "source": "aligned"
    },
    {
      "surah": 96,
      "ayah": 18,
      "start_s": 74.7755,
      "end_s": 77.34,
      "source": "aligned"
    },
    {
      "surah": 96,
      "ayah": 19,
      "start_s": 77.69350000000001,
      "end_s": 83.107,
      "source": "aligned"
    }
  ],
  "words": [
    {
      "surah": 96,
      "ayah": 1,
      "word_index_global": 1,
      "word_index_in_ayah": 1,
      "text_uthmani": "ٱقۡرَأۡ",
      "text_norm": "اقرا",
      "start_s": 0.04800000000000001,
      "end_s": 0.821,
      "confidence": null,
      "alignment_origin": "native",
      "match_score": 100.0,
      "engine_candidate": "nemo",
      "source_start_s": 0.0,
      "source_end_s": 0.83,
      "source_provider": "quran_com"
    },
    {
      "surah": 96,
      "ayah": 1,
      "word_index_global": 2,
      "word_index_in_ayah": 2,
      "text_uthmani": "بِٱسۡمِ",
      "text_norm": "باسم",
      "start_s": 0.845,
      "end_s": 1.391,
      "confidence": null,
      "alignment_origin": "native",
      "match_score": 100.0,
      "engine_candidate": "nemo",
      "source_start_s": 0.83,
      "source_end_s": 1.37,
      "source_provider": "quran_com"
    },
    {
      "surah": 96,
      "ayah": 1,
      "word_index_global": 3,
      "word_index_in_ayah": 3,
      "text_uthmani": "رَبِّكَ",
      "text_norm": "ربك",
      "start_s": 1.415,
      "end_s": 2.223,
      "confidence": null,
      "alignment_origin": "native",
      "match_score": 100.0,
      "engine_candidate": "nemo",
      "source_start_s": 1.37,
      "source_end_s": 2.25,
      "source_provider": "quran_com"
    },
    {
      "surah": 96,
      "ayah": 1,
      "word_index_global": 4,
      "word_index_in_ayah": 4,
      "text_uthmani": "ٱلَّذِی",
      "text_norm": "الذي",
      "start_s": 2.295,
      "end_s": 2.879,
      "confidence": null,
      "alignment_origin": "native",
      "match_score": 100.0,
      "engine_candidate": "nemo",
      "source_start_s": 2.25,
      "source_end_s": 3.05,
      "source_provider": "quran_com"
    },
    {
      "surah": 96,
      "ayah": 1,
      "word_index_global": 5,
      "word_index_in_ayah": 5,
      "text_uthmani": "خَلَقَ",
      "text_norm": "خلق",
      "start_s": 3.0469999999999997,
      "end_s": 3.9635,
      "confidence": null,
      "alignment_origin": "native",
      "match_score": 100.0,
      "engine_candidate": "nemo",
      "source_start_s": 3.05,
      "source_end_s": 4.325,
      "source_provider": "quran_com"
    },
    {
      "surah": 96,
      "ayah": 2,
      "word_index_global": 6,
      "word_index_in_ayah": 1,
      "text_uthmani": "خَلَقَ",
      "text_norm": "خلق",
      "start_s": 4.3955,
      "end_s": 4.9515,
      "confidence": null,
      "alignment_origin": "native",
      "match_score": 100.0,
      "engine_candidate": "nemo",
      "source_start_s": 4.325,
      "source_end_s": 5.085,
      "source_provider": "quran_com"
    },
    {
      "surah": 96,
      "ayah": 2,
      "word_index_global": 7,
      "word_index_in_ayah": 2,
      "text_uthmani": "ٱلۡإِنسَـٰنَ",
      "text_norm": "الانسن",
      "start_s": 5.1915000000000004,
      "end_s": 6.8575,
      "confidence": null,
      "alignment_origin": "native",
      "match_score": 100.0,
      "engine_candidate": "nemo",
      "source_start_s": 5.085,
      "source_end_s": 6.985,
      "source_provider": "quran_com"
    },
    {
      "surah": 96,
      "ayah": 2,
      "word_index_global": 8,
      "word_index_in_ayah": 3,
      "text_uthmani": "مِنۡ",
      "text_norm": "من",
      "start_s": 7.025500000000001,
      "end_s": 7.3575,
      "confidence": null,
      "alignment_origin": "native",
      "match_score": 100.0,
      "engine_candidate": "nemo",
      "source_start_s": 6.985,
      "source_end_s": 7.425,
      "source_provider": "quran_com"
    },
    {
      "surah": 96,
      "ayah": 2,
      "word_index_global": 9,
      "word_index_in_ayah": 4,
      "text_uthmani": "عَلَقٍ",
      "text_norm": "علق",
      "start_s": 7.4535,
      "end_s": 8.521,
      "confidence": null,
      "alignment_origin": "native",
      "match_score": 100.0,
      "engine_candidate": "nemo",
      "source_start_s": 7.425,
      "source_end_s": 8.71,
      "source_provider": "quran_com"
    },
    {
      "surah": 96,
      "ayah": 3,
      "word_index_global": 10,
      "word_index_in_ayah": 1,
      "text_uthmani": "ٱقۡرَأۡ",
      "text_norm": "اقرا",
      "start_s": 8.785499999999999,
      "end_s": 9.5935,
      "confidence": null,
      "alignment_origin": "native",
      "match_score": 100.0,
      "engine_candidate": "nemo",
      "source_start_s": 8.745,
      "source_end_s": 9.625,
      "source_provider": "quran_com"
    },
    {
      "surah": 96,
      "ayah": 3,
      "word_index_global": 11,
      "word_index_in_ayah": 2,
      "text_uthmani": "وَرَبُّكَ",
      "text_norm": "وربك",
      "start_s": 9.6415,
      "end_s": 10.5565,
      "confidence": null,
      "alignment_origin": "native",
      "match_score": 100.0,
      "engine_candidate": "nemo",
      "source_start_s": 9.625,
      "source_end_s": 10.555,
      "source_provider": "quran_com"
    },
    {
      "surah": 96,
      "ayah": 3,
      "word_index_global": 12,
      "word_index_in_ayah": 3,
      "text_uthmani": "ٱلۡأَكۡرَمُ",
      "text_norm": "الاكرم",
      "start_s": 10.6525,
      "end_s": 11.943,
      "confidence": null,
      "alignment_origin": "native",
      "match_score": 100.0,
      "engine_candidate": "nemo",
      "source_start_s": 10.555,
      "source_end_s": 12.09,
      "source_provider": "quran_com"
    },
    {
      "surah": 96,
      "ayah": 4,
      "word_index_global": 13,
      "word_index_in_ayah": 1,
      "text_uthmani": "ٱلَّذِی",
      "text_norm": "الذي",
      "start_s": 12.269499999999999,
      "end_s": 13.035499999999999,
      "confidence": null,
      "alignment_origin": "native",
      "match_score": 100.0,
      "engine_candidate": "nemo",
      "source_start_s": 12.145,
      "source_end_s": 13.205,
      "source_provider": "quran_com"
    },
    {
      "surah": 96,
      "ayah": 4,
      "word_index_global": 14,
      "word_index_in_ayah": 2,
      "text_uthmani": "عَلَّمَ",
      "text_norm": "علم",
      "start_s": 13.2275,
      "end_s": 13.846499999999999,
      "confidence": null,
      "alignment_origin": "native",
      "match_score": 100.0,
      "engine_candidate": "nemo",
      "source_start_s": 13.205,
      "source_end_s": 14.055,
      "source_provider": "quran_com"
    },
    {
      "surah": 96,
      "ayah": 4,
      "word_index_global": 15,
      "word_index_in_ayah": 3,
      "text_uthmani": "بِٱلۡقَلَمِ",
      "text_norm": "بالقلم",
      "start_s": 14.0625,
      "end_s": 15.019000000000002,
      "confidence": null,
      "alignment_origin": "native",
      "match_score": 100.0,
      "engine_candidate": "nemo",
      "source_start_s": 14.055,
      "source_end_s": 15.01,
      "source_provider": "quran_com"
    },
    {
      "surah": 96,
      "ayah": 5,
      "word_index_global": 16,
      "word_index_in_ayah": 1,
      "text_uthmani": "عَلَّمَ",
      "text_norm": "علم",
      "start_s": 15.2975,
      "end_s": 15.9515,
      "confidence": null,
      "alignment_origin": "native",
      "match_score": 100.0,
      "engine_candidate": "nemo",
      "source_start_s": 15.065,
      "source_end_s": 15.965,
      "source_provider": "quran_com"
    },
    {
      "surah": 96,
      "ayah": 5,
      "word_index_global": 17,
      "word_index_in_ayah": 2,
      "text_uthmani": "ٱلۡإِنسَـٰنَ",
      "text_norm": "الانسن",
      "start_s": 16.2395,
      "end_s": 18.1485,
      "confidence": null,
      "alignment_origin": "native",
      "match_score": 100.0,
      "engine_candidate": "nemo",
      "source_start_s": 15.965,
      "source_end_s": 18.075,
      "source_provider": "quran_com"
    },
    {
      "surah": 96,
      "ayah": 5,
      "word_index_global": 18,
      "word_index_in_ayah": 3,
      "text_uthmani": "مَا",
      "text_norm": "ما",
      "start_s": 18.2445,
      "end_s": 18.5065,
      "confidence": null,
      "alignment_origin": "native",
      "match_score": 100.0,
      "engine_candidate": "nemo",
      "source_start_s": 18.075,
      "source_end_s": 18.415,
      "source_provider": "quran_com"
    },
    {
      "surah": 96,
      "ayah": 5,
      "word_index_global": 19,
      "word_index_in_ayah": 4,
      "text_uthmani": "لَمۡ",
      "text_norm": "لم",
      "start_s": 18.578500000000002,
      "end_s": 18.8965,
      "confidence": null,
      "alignment_origin": "native",
      "match_score": 100.0,
      "engine_candidate": "nemo",
      "source_start_s": 18.415,
      "source_end_s": 18.835,
      "source_provider": "quran_com"
    },
    {
      "surah": 96,
      "ayah": 5,
      "word_index_global": 20,
      "word_index_in_ayah": 5,
      "text_uthmani": "یَعۡلَمۡ",
      "text_norm": "يعلم",
      "start_s": 19.0165,
      "end_s": 19.704,
      "confidence": null,
      "alignment_origin": "native",
      "match_score": 100.0,
      "engine_candidate": "nemo",
      "source_start_s": 18.835,
      "source_end_s": 19.68,
      "source_provider": "quran_com"
    },
    {
      "surah": 96,
      "ayah": 6,
      "word_index_global": 21,
      "word_index_in_ayah": 1,
      "text_uthmani": "كَلَّاۤ",
      "text_norm": "كلا",
      "start_s": 20.4045,
      "end_s": 22.214499999999997,
      "confidence": null,
      "alignment_origin": "native",
      "match_score": 100.0,
      "engine_candidate": "nemo",
      "source_start_s": 20.235,
      "source_end_s": 22.615,
      "source_provider": "quran_com"
    },
    {
      "surah": 96,
      "ayah": 6,
      "word_index_global": 22,
      "word_index_in_ayah": 2,
      "text_uthmani": "إِنَّ",
      "text_norm": "ان",
      "start_s": 22.7665,
      "end_s": 23.5255,
      "confidence": null,
      "alignment_origin": "native",
      "match_score": 100.0,
      "engine_candidate": "nemo",
      "source_start_s": 22.615,
      "source_end_s": 23.665,
      "source_provider": "quran_com"
    },
    {
      "surah": 96,
      "ayah": 6,
      "word_index_global": 23,
      "word_index_in_ayah": 3,
      "text_uthmani": "ٱلۡإِنسَـٰنَ",
      "text_norm": "الانسن",
      "start_s": 23.9095,
      "end_s": 25.752499999999998,
      "confidence": null,
      "alignment_origin": "native",
      "match_score": 100.0,
      "engine_candidate": "nemo",
      "source_start_s": 23.665,
      "source_end_s": 25.715,
      "source_provider": "quran_com"
    },
    {
      "surah": 96,
      "ayah": 6,
      "word_index_global": 24,
      "word_index_in_ayah": 4,
      "text_uthmani": "لَیَطۡغَىٰۤ",
      "text_norm": "ليطغي",
      "start_s": 25.8245,
      "end_s": 27.262999999999998,
      "confidence": null,
      "alignment_origin": "native",
      "match_score": 100.0,
      "engine_candidate": "nemo",
      "source_start_s": 25.715,
      "source_end_s": 27.29,
      "source_provider": "quran_com"
    },
    {
      "surah": 96,
      "ayah": 7,
      "word_index_global": 25,
      "word_index_in_ayah": 1,
      "text_uthmani": "أَن",
      "text_norm": "ان",
      "start_s": 27.7765,
      "end_s": 28.0105,
      "confidence": null,
      "alignment_origin": "native",
      "match_score": 100.0,
      "engine_candidate": "nemo",
      "source_start_s": 27.715,
      "source_end_s": 28.015,
      "source_provider": "quran_com"
    },
    {
      "surah": 96,
      "ayah": 7,
      "word_index_global": 26,
      "word_index_in_ayah": 2,
      "text_uthmani": "رَّءَاهُ",
      "text_norm": "رءاه",
      "start_s": 28.0825,
      "end_s": 29.012500000000003,
      "confidence": null,
      "alignment_origin": "native",
      "match_score": 100.0,
      "engine_candidate": "nemo",
      "source_start_s": 28.015,
      "source_end_s": 29.035,
      "source_provider": "quran_com"
    },
    {
      "surah": 96,
      "ayah": 7,
      "word_index_global": 27,
      "word_index_in_ayah": 3,
      "text_uthmani": "ٱسۡتَغۡنَىٰۤ",
      "text_norm": "استغني",
      "start_s": 29.060500000000005,
      "end_s": 30.144000000000002,
      "confidence": null,
      "alignment_origin": "native",
      "match_score": 100.0,
      "engine_candidate": "nemo",
      "source_start_s": 29.035,
      "source_end_s": 30.24,
      "source_provider": "quran_com"
    },
    {
      "surah": 96,
      "ayah": 8,
      "word_index_global": 28,
      "word_index_in_ayah": 1,
      "text_uthmani": "إِنَّ",
      "text_norm": "ان",
      "start_s": 30.494500000000002,
      "end_s": 31.3725,
      "confidence": null,
      "alignment_origin": "native",
      "match_score": 100.0,
      "engine_candidate": "nemo",
      "source_start_s": 30.295,
      "source_end_s": 31.515,
      "source_provider": "quran_com"
    },
    {
      "surah": 96,
      "ayah": 8,
      "word_index_global": 29,
      "word_index_in_ayah": 2,
      "text_uthmani": "إِلَىٰ",
      "text_norm": "الي",
      "start_s": 31.6845,
      "end_s": 32.2805,
      "confidence": null,
      "alignment_origin": "native",
      "match_score": 100.0,
      "engine_candidate": "nemo",
      "source_start_s": 31.515,
      "source_end_s": 32.195,
      "source_provider": "quran_com"
    },
    {
      "surah": 96,
      "ayah": 8,
      "word_index_global": 30,
      "word_index_in_ayah": 3,
      "text_uthmani": "رَبِّكَ",
      "text_norm": "ربك",
      "start_s": 32.328500000000005,
      "end_s": 33.0805,
      "confidence": null,
      "alignment_origin": "native",
      "match_score": 100.0,
      "engine_candidate": "nemo",
      "source_start_s": 32.195,
      "source_end_s": 32.995,
      "source_provider": "quran_com"
    },
    {
      "surah": 96,
      "ayah": 8,
      "word_index_global": 31,
      "word_index_in_ayah": 4,
      "text_uthmani": "ٱلرُّجۡعَىٰۤ",
      "text_norm": "الرجعي",
      "start_s": 33.152499999999996,
      "end_s": 34.260000000000005,
      "confidence": null,
      "alignment_origin": "native",
      "match_score": 100.0,
      "engine_candidate": "nemo",
      "source_start_s": 32.995,
      "source_end_s": 34.2,
      "source_provider": "quran_com"
    },
    {
      "surah": 96,
      "ayah": 9,
      "word_index_global": 32,
      "word_index_in_ayah": 1,
      "text_uthmani": "أَرَءَیۡتَ",
      "text_norm": "ارءيت",
      "start_s": 34.7975,
      "end_s": 35.810500000000005,
      "confidence": null,
      "alignment_origin": "native",
      "match_score": 100.0,
      "engine_candidate": "nemo",
      "source_start_s": 34.625,
      "source_end_s": 35.695,
      "source_provider": "quran_com"
    },
    {
      "surah": 96,
      "ayah": 9,
      "word_index_global": 33,
      "word_index_in_ayah": 2,
      "text_uthmani": "ٱلَّذِی",
      "text_norm": "الذي",
      "start_s": 35.8825,
      "end_s": 36.543499999999995,
      "confidence": null,
      "alignment_origin": "native",
      "match_score": 100.0,
      "engine_candidate": "nemo",
      "source_start_s": 35.695,
      "source_end_s": 36.605,
      "source_provider": "quran_com"
    },
    {
      "surah": 96,
      "ayah": 9,
      "word_index_global": 34,
      "word_index_in_ayah": 3,
      "text_uthmani": "یَنۡهَىٰ",
      "text_norm": "ينهي",
      "start_s": 36.7355,
      "end_s": 37.606,
      "confidence": null,
      "alignment_origin": "native",
      "match_score": 100.0,
      "engine_candidate": "nemo",
      "source_start_s": 36.605,
      "source_end_s": 37.54,
      "source_provider": "quran_com"
    },
    {
      "surah": 96,
      "ayah": 10,
      "word_index_global": 35,
      "word_index_in_ayah": 1,
      "text_uthmani": "عَبۡدًا",
      "text_norm": "عبدا",
      "start_s": 38.1855,
      "end_s": 38.965500000000006,
      "confidence": null,
      "alignment_origin": "native",
      "match_score": 100.0,
      "engine_candidate": "nemo",
      "source_start_s": 38.025,
      "source_end_s": 38.865,
      "source_provider": "quran_com"
    },
    {
      "surah": 96,
      "ayah": 10,
      "word_index_global": 36,
      "word_index_in_ayah": 2,
      "text_uthmani": "إِذَا",
      "text_norm": "اذا",
      "start_s": 39.0135,
      "end_s": 39.5955,
      "confidence": null,
      "alignment_origin": "native",
      "match_score": 100.0,
      "engine_candidate": "nemo",
      "source_start_s": 38.865,
      "source_end_s": 39.525,
      "source_provider": "quran_com"
    },
    {
      "surah": 96,
      "ayah": 10,
      "word_index_global": 37,
      "word_index_in_ayah": 3,
      "text_uthmani": "صَلَّىٰۤ",
      "text_norm": "صلي",
      "start_s": 39.6435,
      "end_s": 40.614999999999995,
      "confidence": null,
      "alignment_origin": "native",
      "match_score": 100.0,
      "engine_candidate": "nemo",
      "source_start_s": 39.525,
      "source_end_s": 40.57,
      "source_provider": "quran_com"
    },
    {
      "surah": 96,
      "ayah": 11,
      "word_index_global": 38,
      "word_index_in_ayah": 1,
      "text_uthmani": "أَرَءَیۡتَ",
      "text_norm": "ارءيت",
      "start_s": 41.0585,
      "end_s": 42.0155,
      "confidence": null,
      "alignment_origin": "native",
      "match_score": 100.0,
      "engine_candidate": "nemo",
      "source_start_s": 40.895,
      "source_end_s": 41.885,
      "source_provider": "quran_com"
    },
    {
      "surah": 96,
      "ayah": 11,
      "word_index_global": 39,
      "word_index_in_ayah": 2,
      "text_uthmani": "إِن",
      "text_norm": "ان",
      "start_s": 42.063500000000005,
      "end_s": 42.8295,
      "confidence": null,
      "alignment_origin": "native",
      "match_score": 100.0,
      "engine_candidate": "nemo",
      "source_start_s": 41.885,
      "source_end_s": 42.945,
      "source_provider": "quran_com"
    },
    {
      "surah": 96,
      "ayah": 11,
      "word_index_global": 40,
      "word_index_in_ayah": 3,
      "text_uthmani": "كَانَ",
      "text_norm": "كان",
      "start_s": 43.0935,
      "end_s": 43.5865,
      "confidence": null,
      "alignment_origin": "native",
      "match_score": 100.0,
      "engine_candidate": "nemo",
      "source_start_s": 42.945,
      "source_end_s": 43.615,
      "source_provider": "quran_com"
    },
    {
      "surah": 96,
      "ayah": 11,
      "word_index_global": 41,
      "word_index_in_ayah": 4,
      "text_uthmani": "عَلَى",
      "text_norm": "علي",
      "start_s": 43.7545,
      "end_s": 44.002500000000005,
      "confidence": null,
      "alignment_origin": "native",
      "match_score": 100.0,
      "engine_candidate": "nemo",
      "source_start_s": 43.615,
      "source_end_s": 43.935,
      "source_provider": "quran_com"
    },
    {
      "surah": 96,
      "ayah": 11,
      "word_index_global": 42,
      "word_index_in_ayah": 5,
      "text_uthmani": "ٱلۡهُدَىٰۤ",
      "text_norm": "الهدي",
      "start_s": 44.1225,
      "end_s": 44.977000000000004,
      "confidence": null,
      "alignment_origin": "native",
      "match_score": 100.0,
      "engine_candidate": "nemo",
      "source_start_s": 43.935,
      "source_end_s": 44.95,
      "source_provider": "quran_com"
    },
    {
      "surah": 96,
      "ayah": 12,
      "word_index_global": 43,
      "word_index_in_ayah": 1,
      "text_uthmani": "أَوۡ",
      "text_norm": "او",
      "start_s": 45.5565,
      "end_s": 45.8885,
      "confidence": null,
      "alignment_origin": "native",
      "match_score": 100.0,
      "engine_candidate": "nemo",
      "source_start_s": 45.435,
      "source_end_s": 45.875,
      "source_provider": "quran_com"
    },
    {
      "surah": 96,
      "ayah": 12,
      "word_index_global": 44,
      "word_index_in_ayah": 2,
      "text_uthmani": "أَمَرَ",
      "text_norm": "امر",
      "start_s": 46.0085,
      "end_s": 46.5425,
      "confidence": null,
      "alignment_origin": "native",
      "match_score": 100.0,
      "engine_candidate": "nemo",
      "source_start_s": 45.875,
      "source_end_s": 46.535,
      "source_provider": "quran_com"
    },
    {
      "surah": 96,
      "ayah": 12,
      "word_index_global": 45,
      "word_index_in_ayah": 3,
      "text_uthmani": "بِٱلتَّقۡوَىٰۤ",
      "text_norm": "بالتقوي",
      "start_s": 46.662499999999994,
      "end_s": 47.913000000000004,
      "confidence": null,
      "alignment_origin": "native",
      "match_score": 100.0,
      "engine_candidate": "nemo",
      "source_start_s": 46.535,
      "source_end_s": 47.91,
      "source_provider": "quran_com"
    },
    {
      "surah": 96,
      "ayah": 13,
      "word_index_global": 46,
      "word_index_in_ayah": 1,
      "text_uthmani": "أَرَءَیۡتَ",
      "text_norm": "ارءيت",
      "start_s": 48.4465,
      "end_s": 49.4525,
      "confidence": null,
      "alignment_origin": "native",
      "match_score": 100.0,
      "engine_candidate": "nemo",
      "source_start_s": 48.295,
      "source_end_s": 49.355,
      "source_provider": "quran_com"
    },
    {
      "surah": 96,
      "ayah": 13,
      "word_index_global": 47,
      "word_index_in_ayah": 2,
      "text_uthmani": "إِن",
      "text_norm": "ان",
      "start_s": 49.5245,
      "end_s": 50.269499999999994,
      "confidence": null,
      "alignment_origin": "native",
      "match_score": 100.0,
      "engine_candidate": "nemo",
      "source_start_s": 49.355,
      "source_end_s": 50.385,
      "source_provider": "quran_com"
    },
    {
      "surah": 96,
      "ayah": 13,
      "word_index_global": 48,
      "word_index_in_ayah": 3,
      "text_uthmani": "كَذَّبَ",
      "text_norm": "كذب",
      "start_s": 50.485499999999995,
      "end_s": 51.19350000000001,
      "confidence": null,
      "alignment_origin": "native",
      "match_score": 100.0,
      "engine_candidate": "nemo",
      "source_start_s": 50.385,
      "source_end_s": 51.225,
      "source_provider": "quran_com"
    },
    {
      "surah": 96,
      "ayah": 13,
      "word_index_global": 49,
      "word_index_in_ayah": 4,
      "text_uthmani": "وَتَوَلَّىٰۤ",
      "text_norm": "وتولي",
      "start_s": 51.36150000000001,
      "end_s": 52.559000000000005,
      "confidence": null,
      "alignment_origin": "native",
      "match_score": 100.0,
      "engine_candidate": "nemo",
      "source_start_s": 51.225,
      "source_end_s": 52.49,
      "source_provider": "quran_com"
    },
    {
      "surah": 96,
      "ayah": 14,
      "word_index_global": 50,
      "word_index_in_ayah": 1,
      "text_uthmani": "أَلَمۡ",
      "text_norm": "الم",
      "start_s": 53.09349999999999,
      "end_s": 53.530499999999996,
      "confidence": null,
      "alignment_origin": "native",
      "match_score": 100.0,
      "engine_candidate": "nemo",
      "source_start_s": 52.945,
      "source_end_s": 53.535,
      "source_provider": "quran_com"
    },
    {
      "surah": 96,
      "ayah": 14,
      "word_index_global": 51,
      "word_index_in_ayah": 2,
      "text_uthmani": "یَعۡلَم",
      "text_norm": "يعلم",
      "start_s": 53.674499999999995,
      "end_s": 54.8695,
      "confidence": null,
      "alignment_origin": "native",
      "match_score": 100.0,
      "engine_candidate": "nemo",
      "source_start_s": 53.535,
      "source_end_s": 55.105,
      "source_provider": "quran_com"
    },
    {
      "surah": 96,
      "ayah": 14,
      "word_index_global": 52,
      "word_index_in_ayah": 3,
      "text_uthmani": "بِأَنَّ",
      "text_norm": "بان",
      "start_s": 55.2535,
      "end_s": 56.4435,
      "confidence": null,
      "alignment_origin": "native",
      "match_score": 100.0,
      "engine_candidate": "nemo",
      "source_start_s": 55.105,
      "source_end_s": 56.565,
      "source_provider": "quran_com"
    },
    {
      "surah": 96,
      "ayah": 14,
      "word_index_global": 53,
      "word_index_in_ayah": 4,
      "text_uthmani": "ٱللَّهَ",
      "text_norm": "الله",
      "start_s": 56.707499999999996,
      "end_s": 57.3055,
      "confidence": null,
      "alignment_origin": "native",
      "match_score": 100.0,
      "engine_candidate": "nemo",
      "source_start_s": 56.565,
      "source_end_s": 57.385,
      "source_provider": "quran_com"
    },
    {
      "surah": 96,
      "ayah": 14,
      "word_index_global": 54,
      "word_index_in_ayah": 5,
      "text_uthmani": "یَرَىٰ",
      "text_norm": "يري",
      "start_s": 57.4975,
      "end_s": 58.391000000000005,
      "confidence": null,
      "alignment_origin": "native",
      "match_score": 100.0,
      "engine_candidate": "nemo",
      "source_start_s": 57.385,
      "source_end_s": 58.49,
      "source_provider": "quran_com"
    },
    {
      "surah": 96,
      "ayah": 15,
      "word_index_global": 55,
      "word_index_in_ayah": 1,
      "text_uthmani": "كَلَّا",
      "text_norm": "كلا",
      "start_s": 58.917500000000004,
      "end_s": 59.7995,
      "confidence": null,
      "alignment_origin": "native",
      "match_score": 100.0,
      "engine_candidate": "nemo",
      "source_start_s": 58.865,
      "source_end_s": 59.885,
      "source_provider": "quran_com"
    },
    {
      "surah": 96,
      "ayah": 15,
      "word_index_global": 56,
      "word_index_in_ayah": 2,
      "text_uthmani": "لَئِن",
      "text_norm": "لين",
      "start_s": 60.039500000000004,
      "end_s": 60.8035,
      "confidence": null,
      "alignment_origin": "native",
      "match_score": 100.0,
      "engine_candidate": "nemo",
      "source_start_s": 59.885,
      "source_end_s": 60.805,
      "source_provider": "quran_com"
    },
    {
      "surah": 96,
      "ayah": 15,
      "word_index_global": 57,
      "word_index_in_ayah": 3,
      "text_uthmani": "لَّمۡ",
      "text_norm": "لم",
      "start_s": 60.8515,
      "end_s": 61.23950000000001,
      "confidence": null,
      "alignment_origin": "native",
      "match_score": 100.0,
      "engine_candidate": "nemo",
      "source_start_s": 60.805,
      "source_end_s": 61.325,
      "source_provider": "quran_com"
    },
    {
      "surah": 96,
      "ayah": 15,
      "word_index_global": 58,
      "word_index_in_ayah": 4,
      "text_uthmani": "یَنتَهِ",
      "text_norm": "ينته",
      "start_s": 61.359500000000004,
      "end_s": 62.7315,
      "confidence": null,
      "alignment_origin": "native",
      "match_score": 100.0,
      "engine_candidate": "nemo",
      "source_start_s": 61.325,
      "source_end_s": 62.805,
      "source_provider": "quran_com"
    },
    {
      "surah": 96,
      "ayah": 15,
      "word_index_global": 59,
      "word_index_in_ayah": 5,
      "text_uthmani": "لَنَسۡفَعَۢا",
      "text_norm": "لنسفعا",
      "start_s": 62.8035,
      "end_s": 64.1265,
      "confidence": null,
      "alignment_origin": "native",
      "match_score": 100.0,
      "engine_candidate": "nemo",
      "source_start_s": 62.805,
      "source_end_s": 64.215,
      "source_provider": "quran_com"
    },
    {
      "surah": 96,
      "ayah": 15,
      "word_index_global": 60,
      "word_index_in_ayah": 6,
      "text_uthmani": "بِٱلنَّاصِیَةِ",
      "text_norm": "بالناصية",
      "start_s": 64.3665,
      "end_s": 67.366,
      "confidence": null,
      "alignment_origin": "native",
      "match_score": 100.0,
      "engine_candidate": "nemo",
      "source_start_s": 64.215,
      "source_end_s": 67.54,
      "source_provider": "quran_com"
    },
    {
      "surah": 96,
      "ayah": 16,
      "word_index_global": 61,
      "word_index_in_ayah": 1,
      "text_uthmani": "نَاصِیَةࣲ",
      "text_norm": "ناصية",
      "start_s": 67.6135,
      "end_s": 69.2735,
      "confidence": null,
      "alignment_origin": "native",
      "match_score": 100.0,
      "engine_candidate": "nemo",
      "source_start_s": 67.585,
      "source_end_s": 69.545,
      "source_provider": "quran_com"
    },
    {
      "surah": 96,
      "ayah": 16,
      "word_index_global": 62,
      "word_index_in_ayah": 2,
      "text_uthmani": "كَـٰذِبَةٍ",
      "text_norm": "كذبة",
      "start_s": 69.5375,
      "end_s": 70.6725,
      "confidence": null,
      "alignment_origin": "native",
      "match_score": 100.0,
      "engine_candidate": "nemo",
      "source_start_s": 69.545,
      "source_end_s": 70.755,
      "source_provider": "quran_com"
    },
    {
      "surah": 96,
      "ayah": 16,
      "word_index_global": 63,
      "word_index_in_ayah": 3,
      "text_uthmani": "خَاطِئَةࣲ",
      "text_norm": "خاطية",
      "start_s": 70.76849999999999,
      "end_s": 72.06800000000001,
      "confidence": null,
      "alignment_origin": "native",
      "match_score": 100.0,
      "engine_candidate": "nemo",
      "source_start_s": 70.755,
      "source_end_s": 72.2,
      "source_provider": "quran_com"
    },
    {
      "surah": 96,
      "ayah": 17,
      "word_index_global": 64,
      "word_index_in_ayah": 1,
      "text_uthmani": "فَلۡیَدۡعُ",
      "text_norm": "فليدع",
      "start_s": 72.2535,
      "end_s": 73.2805,
      "confidence": null,
      "alignment_origin": "native",
      "match_score": 100.0,
      "engine_candidate": "nemo",
      "source_start_s": 72.225,
      "source_end_s": 73.315,
      "source_provider": "quran_com"
    },
    {
      "surah": 96,
      "ayah": 17,
      "word_index_global": 65,
      "word_index_in_ayah": 2,
      "text_uthmani": "نَادِیَهُۥ",
      "text_norm": "ناديه",
      "start_s": 73.35249999999999,
      "end_s": 74.607,
      "confidence": null,
      "alignment_origin": "native",
      "match_score": 100.0,
      "engine_candidate": "nemo",
      "source_start_s": 73.315,
      "source_end_s": 74.73,
      "source_provider": "quran_com"
    },
    {
      "surah": 96,
      "ayah": 18,
      "word_index_global": 66,
      "word_index_in_ayah": 1,
      "text_uthmani": "سَنَدۡعُ",
      "text_norm": "سندع",
      "start_s": 74.7755,
      "end_s": 75.6175,
      "confidence": null,
      "alignment_origin": "native",
      "match_score": 100.0,
      "engine_candidate": "nemo",
      "source_start_s": 74.765,
      "source_end_s": 75.625,
      "source_provider": "quran_com"
    },
    {
      "surah": 96,
      "ayah": 18,
      "word_index_global": 67,
      "word_index_in_ayah": 2,
      "text_uthmani": "ٱلزَّبَانِیَةَ",
      "text_norm": "الزبانية",
      "start_s": 75.68950000000001,
      "end_s": 77.34,
      "confidence": null,
      "alignment_origin": "native",
      "match_score": 100.0,
      "engine_candidate": "nemo",
      "source_start_s": 75.625,
      "source_end_s": 77.64,
      "source_provider": "quran_com"
    },
    {
      "surah": 96,
      "ayah": 19,
      "word_index_global": 68,
      "word_index_in_ayah": 1,
      "text_uthmani": "كَلَّا",
      "text_norm": "كلا",
      "start_s": 77.69350000000001,
      "end_s": 78.4985,
      "confidence": null,
      "alignment_origin": "native",
      "match_score": 100.0,
      "engine_candidate": "nemo",
      "source_start_s": 77.665,
      "source_end_s": 78.575,
      "source_provider": "quran_com"
    },
    {
      "surah": 96,
      "ayah": 19,
      "word_index_global": 69,
      "word_index_in_ayah": 2,
      "text_uthmani": "لَا",
      "text_norm": "لا",
      "start_s": 78.57050000000001,
      "end_s": 78.8745,
      "confidence": null,
      "alignment_origin": "native",
      "match_score": 100.0,
      "engine_candidate": "nemo",
      "source_start_s": 78.575,
      "source_end_s": 78.975,
      "source_provider": "quran_com"
    },
    {
      "surah": 96,
      "ayah": 19,
      "word_index_global": 70,
      "word_index_in_ayah": 3,
      "text_uthmani": "تُطِعۡهُ",
      "text_norm": "تطعه",
      "start_s": 78.9705,
      "end_s": 79.9555,
      "confidence": null,
      "alignment_origin": "native",
      "match_score": 100.0,
      "engine_candidate": "nemo",
      "source_start_s": 78.975,
      "source_end_s": 80.005,
      "source_provider": "quran_com"
    },
    {
      "surah": 96,
      "ayah": 19,
      "word_index_global": 71,
      "word_index_in_ayah": 4,
      "text_uthmani": "وَ̅ٱ̅سۡ̅جُ̅دۡ̅",
      "text_norm": "واسجد",
      "start_s": 80.0035,
      "end_s": 80.7385,
      "confidence": null,
      "alignment_origin": "native",
      "match_score": 100.0,
      "engine_candidate": "nemo",
      "source_start_s": 80.005,
      "source_end_s": 80.815,
      "source_provider": "quran_com"
    },
    {
      "surah": 96,
      "ayah": 19,
      "word_index_global": 72,
      "word_index_in_ayah": 5,
      "text_uthmani": "وَٱقۡتَرِب",
      "text_norm": "واقترب",
      "start_s": 80.8585,
      "end_s": 83.107,
      "confidence": null,
      "alignment_origin": "native",
      "match_score": 100.0,
      "engine_candidate": "nemo",
      "source_start_s": 80.815,
      "source_end_s": 83.65,
      "source_provider": "quran_com"
    }
  ]
}
