{
  "schema_version": "v2",
  "reciter": {
    "slug": "muhsin_al_qasim",
    "name": "Muhsin Al Qasim"
  },
  "surah": {
    "number": 88,
    "title": "Surah 88",
    "ayah_count": 26,
    "word_count": 92
  },
  "audio": {
    "granularity": "ayah",
    "primary_asset": "everyayah_ayah",
    "fallback_order": [],
    "assets": {
      "everyayah_ayah": {
        "provider": "everyayah",
        "level": "ayah",
        "kind": "template",
        "template": "https://everyayah.com/data/Muhsin_Al_Qasim_192kbps/088{ayah:03d}.mp3"
      }
    },
    "duration_s": 94.7080045351474,
    "sample_rate": 44100,
    "channels": 2
  },
  "quality": {
    "coverage": 1.0,
    "monotonic": true,
    "duration_match": true,
    "warnings": ["boundary_refinement_applied"],
    "reason_codes": [],
    "zero_or_negative_ratio": 0.0,
    "median_confidence": null,
    "interpolated_ratio": 0.0,
    "lexical_match_ratio": 1.0,
    "speech_end_delta_ratio": 0.003998314825560637,
    "quantization_step_ms": 480.000000000002,
    "everyayah_stitch_eval": {
      "expected_ayahs": 26,
      "predicted_ayahs": 26,
      "matched_ayahs": 26,
      "coverage_vs_reference": 1.0,
      "start_error_median_ms": 102.417,
      "end_error_median_ms": 379.978,
      "boundary_error_median_ms": 238.625,
      "boundary_error_p95_ms": 800.766,
      "boundary_hit_rate_20ms": 0.057692,
      "boundary_hit_rate_50ms": 0.096154,
      "boundary_hit_rate_80ms": 0.211538,
      "start_offset_s": -0.041687,
      "offset_normalized_boundary_error_median_ms": 196.938,
      "offset_normalized_boundary_error_p95_ms": 759.079,
      "offset_normalized_hit_rate_20ms": 0.057692,
      "offset_normalized_hit_rate_50ms": 0.173077,
      "offset_normalized_hit_rate_80ms": 0.269231,
      "ayah_differences": [
        {
          "ayah": 1,
          "pred_start_s": 0.26,
          "pred_end_s": 3.225,
          "ref_start_s": 0.0,
          "ref_end_s": 3.48,
          "delta_start_ms": 260.0,
          "delta_end_ms": -254.625,
          "abs_start_ms": 260.0,
          "abs_end_ms": 254.625,
          "norm_delta_start_ms": 301.687,
          "norm_delta_end_ms": -212.938,
          "norm_abs_start_ms": 301.687,
          "norm_abs_end_ms": 212.938
        },
        {
          "ayah": 2,
          "pred_start_s": 3.475,
          "pred_end_s": 7.01,
          "ref_start_s": 3.48,
          "ref_end_s": 7.22,
          "delta_start_ms": -4.625,
          "delta_end_ms": -210.458,
          "abs_start_ms": 4.625,
          "abs_end_ms": 210.458,
          "norm_delta_start_ms": 37.062,
          "norm_delta_end_ms": -168.771,
          "norm_abs_start_ms": 37.062,
          "norm_abs_end_ms": 168.771
        },
        {
          "ayah": 3,
          "pred_start_s": 7.16,
          "pred_end_s": 9.795,
          "ref_start_s": 7.22,
          "ref_end_s": 10.047,
          "delta_start_ms": -60.458,
          "delta_end_ms": -252.0,
          "abs_start_ms": 60.458,
          "abs_end_ms": 252.0,
          "norm_delta_start_ms": -18.771,
          "norm_delta_end_ms": -210.313,
          "norm_abs_start_ms": 18.771,
          "norm_abs_end_ms": 210.313
        },
        {
          "ayah": 4,
          "pred_start_s": 9.93,
          "pred_end_s": 12.27,
          "ref_start_s": 10.047,
          "ref_end_s": 12.56,
          "delta_start_ms": -117.0,
          "delta_end_ms": -290.083,
          "abs_start_ms": 117.0,
          "abs_end_ms": 290.083,
          "norm_delta_start_ms": -75.313,
          "norm_delta_end_ms": -248.396,
          "norm_abs_start_ms": 75.313,
          "norm_abs_end_ms": 248.396
        },
        {
          "ayah": 5,
          "pred_start_s": 12.455,
          "pred_end_s": 15.16,
          "ref_start_s": 12.56,
          "ref_end_s": 15.491,
          "delta_start_ms": -105.083,
          "delta_end_ms": -331.166,
          "abs_start_ms": 105.083,
          "abs_end_ms": 331.166,
          "norm_delta_start_ms": -63.396,
          "norm_delta_end_ms": -289.479,
          "norm_abs_start_ms": 63.396,
          "norm_abs_end_ms": 289.479
        },
        {
          "ayah": 6,
          "pred_start_s": 15.48,
          "pred_end_s": 19.88,
          "ref_start_s": 15.491,
          "ref_end_s": 20.355,
          "delta_start_ms": -11.166,
          "delta_end_ms": -475.249,
          "abs_start_ms": 11.166,
          "abs_end_ms": 475.249,
          "norm_delta_start_ms": 30.521,
          "norm_delta_end_ms": -433.562,
          "norm_abs_start_ms": 30.521,
          "norm_abs_end_ms": 433.562
        },
        {
          "ayah": 7,
          "pred_start_s": 20.245,
          "pred_end_s": 23.945,
          "ref_start_s": 20.355,
          "ref_end_s": 24.723,
          "delta_start_ms": -110.249,
          "delta_end_ms": -778.041,
          "abs_start_ms": 110.249,
          "abs_end_ms": 778.041,
          "norm_delta_start_ms": -68.562,
          "norm_delta_end_ms": -736.354,
          "norm_abs_start_ms": 68.562,
          "norm_abs_end_ms": 736.354
        },
        {
          "ayah": 8,
          "pred_start_s": 24.52,
          "pred_end_s": 28.345,
          "ref_start_s": 24.723,
          "ref_end_s": 28.621,
          "delta_start_ms": -203.041,
          "delta_end_ms": -275.624,
          "abs_start_ms": 203.041,
          "abs_end_ms": 275.624,
          "norm_delta_start_ms": -161.354,
          "norm_delta_end_ms": -233.937,
          "norm_abs_start_ms": 161.354,
          "norm_abs_end_ms": 233.937
        },
        {
          "ayah": 9,
          "pred_start_s": 28.55,
          "pred_end_s": 30.595,
          "ref_start_s": 28.621,
          "ref_end_s": 30.82,
          "delta_start_ms": -70.624,
          "delta_end_ms": -225.249,
          "abs_start_ms": 70.624,
          "abs_end_ms": 225.249,
          "norm_delta_start_ms": -28.937,
          "norm_delta_end_ms": -183.562,
          "norm_abs_start_ms": 28.937,
          "norm_abs_end_ms": 183.562
        },
        {
          "ayah": 10,
          "pred_start_s": 30.92,
          "pred_end_s": 33.475,
          "ref_start_s": 30.82,
          "ref_end_s": 33.673,
          "delta_start_ms": 99.751,
          "delta_end_ms": -197.916,
          "abs_start_ms": 99.751,
          "abs_end_ms": 197.916,
          "norm_delta_start_ms": 141.438,
          "norm_delta_end_ms": -156.229,
          "norm_abs_start_ms": 141.438,
          "norm_abs_end_ms": 156.229
        },
        {
          "ayah": 11,
          "pred_start_s": 33.65,
          "pred_end_s": 36.635,
          "ref_start_s": 33.673,
          "ref_end_s": 37.022,
          "delta_start_ms": -22.916,
          "delta_end_ms": -386.916,
          "abs_start_ms": 22.916,
          "abs_end_ms": 386.916,
          "norm_delta_start_ms": 18.771,
          "norm_delta_end_ms": -345.229,
          "norm_abs_start_ms": 18.771,
          "norm_abs_end_ms": 345.229
        },
        {
          "ayah": 12,
          "pred_start_s": 37.0,
          "pred_end_s": 39.755,
          "ref_start_s": 37.022,
          "ref_end_s": 40.293,
          "delta_start_ms": -21.916,
          "delta_end_ms": -537.583,
          "abs_start_ms": 21.916,
          "abs_end_ms": 537.583,
          "norm_delta_start_ms": 19.771,
          "norm_delta_end_ms": -495.896,
          "norm_abs_start_ms": 19.771,
          "norm_abs_end_ms": 495.896
        },
        {
          "ayah": 13,
          "pred_start_s": 40.635,
          "pred_end_s": 43.895,
          "ref_start_s": 40.293,
          "ref_end_s": 44.086,
          "delta_start_ms": 342.417,
          "delta_end_ms": -190.666,
          "abs_start_ms": 342.417,
          "abs_end_ms": 190.666,
          "norm_delta_start_ms": 384.104,
          "norm_delta_end_ms": -148.979,
          "norm_abs_start_ms": 384.104,
          "norm_abs_end_ms": 148.979
        },
        {
          "ayah": 14,
          "pred_start_s": 44.975,
          "pred_end_s": 47.475,
          "ref_start_s": 44.086,
          "ref_end_s": 47.617,
          "delta_start_ms": 889.334,
          "delta_end_ms": -142.499,
          "abs_start_ms": 889.334,
          "abs_end_ms": 142.499,
          "norm_delta_start_ms": 931.021,
          "norm_delta_end_ms": -100.812,
          "norm_abs_start_ms": 931.021,
          "norm_abs_end_ms": 100.812
        },
        {
          "ayah": 15,
          "pred_start_s": 48.075,
          "pred_end_s": 50.28,
          "ref_start_s": 47.617,
          "ref_end_s": 50.653,
          "delta_start_ms": 457.501,
          "delta_end_ms": -373.041,
          "abs_start_ms": 457.501,
          "abs_end_ms": 373.041,
          "norm_delta_start_ms": 499.188,
          "norm_delta_end_ms": -331.354,
          "norm_abs_start_ms": 499.188,
          "norm_abs_end_ms": 331.354
        },
        {
          "ayah": 16,
          "pred_start_s": 50.935,
          "pred_end_s": 53.595,
          "ref_start_s": 50.653,
          "ref_end_s": 54.107,
          "delta_start_ms": 281.959,
          "delta_end_ms": -511.541,
          "abs_start_ms": 281.959,
          "abs_end_ms": 511.541,
          "norm_delta_start_ms": 323.646,
          "norm_delta_end_ms": -469.854,
          "norm_abs_start_ms": 323.646,
          "norm_abs_end_ms": 469.854
        },
        {
          "ayah": 17,
          "pred_start_s": 54.125,
          "pred_end_s": 59.07,
          "ref_start_s": 54.107,
          "ref_end_s": 59.467,
          "delta_start_ms": 18.459,
          "delta_end_ms": -396.999,
          "abs_start_ms": 18.459,
          "abs_end_ms": 396.999,
          "norm_delta_start_ms": 60.146,
          "norm_delta_end_ms": -355.312,
          "norm_abs_start_ms": 60.146,
          "norm_abs_end_ms": 355.312
        },
        {
          "ayah": 18,
          "pred_start_s": 59.4,
          "pred_end_s": 63.12,
          "ref_start_s": 59.467,
          "ref_end_s": 63.338,
          "delta_start_ms": -66.999,
          "delta_end_ms": -218.457,
          "abs_start_ms": 66.999,
          "abs_end_ms": 218.457,
          "norm_delta_start_ms": -25.312,
          "norm_delta_end_ms": -176.77,
          "norm_abs_start_ms": 25.312,
          "norm_abs_end_ms": 176.77
        },
        {
          "ayah": 19,
          "pred_start_s": 63.395,
          "pred_end_s": 66.085,
          "ref_start_s": 63.338,
          "ref_end_s": 66.452,
          "delta_start_ms": 56.543,
          "delta_end_ms": -367.332,
          "abs_start_ms": 56.543,
          "abs_end_ms": 367.332,
          "norm_delta_start_ms": 98.23,
          "norm_delta_end_ms": -325.645,
          "norm_abs_start_ms": 98.23,
          "norm_abs_end_ms": 325.645
        },
        {
          "ayah": 20,
          "pred_start_s": 66.52,
          "pred_end_s": 69.0,
          "ref_start_s": 66.452,
          "ref_end_s": 69.723,
          "delta_start_ms": 67.668,
          "delta_end_ms": -722.999,
          "abs_start_ms": 67.668,
          "abs_end_ms": 722.999,
          "norm_delta_start_ms": 109.355,
          "norm_delta_end_ms": -681.312,
          "norm_abs_start_ms": 109.355,
          "norm_abs_end_ms": 681.312
        },
        {
          "ayah": 21,
          "pred_start_s": 69.655,
          "pred_end_s": 74.605,
          "ref_start_s": 69.723,
          "ref_end_s": 75.188,
          "delta_start_ms": -67.999,
          "delta_end_ms": -582.916,
          "abs_start_ms": 67.999,
          "abs_end_ms": 582.916,
          "norm_delta_start_ms": -26.312,
          "norm_delta_end_ms": -541.229,
          "norm_abs_start_ms": 26.312,
          "norm_abs_end_ms": 541.229
        },
        {
          "ayah": 22,
          "pred_start_s": 75.08,
          "pred_end_s": 77.63,
          "ref_start_s": 75.188,
          "ref_end_s": 78.459,
          "delta_start_ms": -107.916,
          "delta_end_ms": -828.541,
          "abs_start_ms": 107.916,
          "abs_end_ms": 828.541,
          "norm_delta_start_ms": -66.229,
          "norm_delta_end_ms": -786.854,
          "norm_abs_start_ms": 66.229,
          "norm_abs_end_ms": 786.854
        },
        {
          "ayah": 23,
          "pred_start_s": 78.2,
          "pred_end_s": 81.255,
          "ref_start_s": 78.459,
          "ref_end_s": 81.886,
          "delta_start_ms": -258.541,
          "delta_end_ms": -630.916,
          "abs_start_ms": 258.541,
          "abs_end_ms": 630.916,
          "norm_delta_start_ms": -216.854,
          "norm_delta_end_ms": -589.229,
          "norm_abs_start_ms": 216.854,
          "norm_abs_end_ms": 589.229
        },
        {
          "ayah": 24,
          "pred_start_s": 81.72,
          "pred_end_s": 85.48,
          "ref_start_s": 81.886,
          "ref_end_s": 86.201,
          "delta_start_ms": -165.916,
          "delta_end_ms": -721.458,
          "abs_start_ms": 165.916,
          "abs_end_ms": 721.458,
          "norm_delta_start_ms": -124.229,
          "norm_delta_end_ms": -679.771,
          "norm_abs_start_ms": 124.229,
          "norm_abs_end_ms": 679.771
        },
        {
          "ayah": 25,
          "pred_start_s": 86.12,
          "pred_end_s": 89.245,
          "ref_start_s": 86.201,
          "ref_end_s": 89.864,
          "delta_start_ms": -81.458,
          "delta_end_ms": -618.916,
          "abs_start_ms": 81.458,
          "abs_end_ms": 618.916,
          "norm_delta_start_ms": -39.771,
          "norm_delta_end_ms": -577.229,
          "norm_abs_start_ms": 39.771,
          "norm_abs_end_ms": 577.229
        },
        {
          "ayah": 26,
          "pred_start_s": 89.72,
          "pred_end_s": 93.975,
          "ref_start_s": 89.864,
          "ref_end_s": 94.859,
          "delta_start_ms": -143.916,
          "delta_end_ms": -883.666,
          "abs_start_ms": 143.916,
          "abs_end_ms": 883.666,
          "norm_delta_start_ms": -102.229,
          "norm_delta_end_ms": -841.979,
          "norm_abs_start_ms": 102.229,
          "norm_abs_end_ms": 841.979
        }
      ]
    }
  },
  "provenance": {
    "engine": {
      "name": "ensemble",
      "model": "ayah-wise",
      "device": "cpu",
      "fallback_used": true,
      "attempted": ["nemo", "whisperx", "mfa"]
    },
    "selected_candidate_engine": "ensemble",
    "candidate_scores": {
      "nemo": 177.90028900718596,
      "mfa": 177.90028900718596
    },
    "pass_trace": [
      "A_audio_normalization",
      "B_ayah_anchors",
      "C_word_candidates",
      "D_candidate_fusion",
      "E_boundary_refinement",
      "F_qc_gates_and_rescue"
    ],
    "supervision_sources": [
      "everyayah:subfolder=Muhsin_Al_Qasim_192kbps:surah=88:scope=full_surah"
    ],
    "segment_source_type": "none"
  },
  "timings_endpoint": "/data/reciters/muhsin_al_qasim/surahs/88/timings.json",
  "updated_at": "2026-03-07T02:03:52.463961+00:00"
}
