{
  "schema_version": "v2",
  "reciter": {
    "slug": "eya_yasser_ad_dussary_128kbps",
    "name": "Yasser_Ad-Dussary"
  },
  "surah": {
    "number": 99,
    "title": "Surah 99",
    "ayah_count": 8,
    "word_count": 36
  },
  "audio": {
    "granularity": "ayah",
    "primary_asset": "everyayah_ayah",
    "fallback_order": [],
    "assets": {
      "everyayah_ayah": {
        "provider": "everyayah",
        "level": "ayah",
        "kind": "template",
        "template": "https://everyayah.com/data/Yasser_Ad-Dussary_128kbps/099{ayah:03d}.mp3"
      }
    },
    "duration_s": 56.09902494331066,
    "sample_rate": 44100,
    "channels": 2
  },
  "quality": {
    "coverage": 1.0,
    "monotonic": true,
    "duration_match": true,
    "warnings": [],
    "reason_codes": [],
    "zero_or_negative_ratio": 0.0,
    "median_confidence": null,
    "interpolated_ratio": 0.0,
    "lexical_match_ratio": 1.0,
    "speech_end_delta_ratio": 0.0006276500151267337,
    "quantization_step_ms": 615.000000000002,
    "boundary_refine_method": "librosa",
    "everyayah_stitch_eval": {
      "expected_ayahs": 8,
      "predicted_ayahs": 8,
      "matched_ayahs": 8,
      "coverage_vs_reference": 1.0,
      "start_error_median_ms": 207.811,
      "end_error_median_ms": 694.72,
      "boundary_error_median_ms": 501.313,
      "boundary_error_p95_ms": 5441.764,
      "boundary_hit_rate_20ms": 0.0625,
      "boundary_hit_rate_50ms": 0.0625,
      "boundary_hit_rate_80ms": 0.0625,
      "start_offset_s": 0.14306,
      "offset_normalized_boundary_error_median_ms": 564.843,
      "offset_normalized_boundary_error_p95_ms": 5298.704,
      "offset_normalized_hit_rate_20ms": 0.125,
      "offset_normalized_hit_rate_50ms": 0.1875,
      "offset_normalized_hit_rate_80ms": 0.1875,
      "ayah_differences": [
        {
          "ayah": 1,
          "pred_start_s": 0.0,
          "pred_end_s": 3.43,
          "ref_start_s": 0.0,
          "ref_end_s": 4.397,
          "delta_start_ms": 0.0,
          "delta_end_ms": -966.563,
          "abs_start_ms": 0.0,
          "abs_end_ms": 966.563,
          "norm_delta_start_ms": -143.06,
          "norm_delta_end_ms": -1109.623,
          "norm_abs_start_ms": 143.06,
          "norm_abs_end_ms": 1109.623
        },
        {
          "ayah": 2,
          "pred_start_s": 4.13,
          "pred_end_s": 7.16,
          "ref_start_s": 4.397,
          "ref_end_s": 7.774,
          "delta_start_ms": -266.563,
          "delta_end_ms": -614.376,
          "abs_start_ms": 266.563,
          "abs_end_ms": 614.376,
          "norm_delta_start_ms": -409.623,
          "norm_delta_end_ms": -757.436,
          "norm_abs_start_ms": 409.623,
          "norm_abs_end_ms": 757.436
        },
        {
          "ayah": 3,
          "pred_start_s": 8.2,
          "pred_end_s": 12.665,
          "ref_start_s": 7.774,
          "ref_end_s": 13.555,
          "delta_start_ms": 425.624,
          "delta_end_ms": -890.439,
          "abs_start_ms": 425.624,
          "abs_end_ms": 890.439,
          "norm_delta_start_ms": 282.564,
          "norm_delta_end_ms": -1033.499,
          "norm_abs_start_ms": 282.564,
          "norm_abs_end_ms": 1033.499
        },
        {
          "ayah": 4,
          "pred_start_s": 18.795,
          "pred_end_s": 22.44,
          "ref_start_s": 13.555,
          "ref_end_s": 22.628,
          "delta_start_ms": 5239.561,
          "delta_end_ms": -187.939,
          "abs_start_ms": 5239.561,
          "abs_end_ms": 187.939,
          "norm_delta_start_ms": 5096.501,
          "norm_delta_end_ms": -331.0,
          "norm_abs_start_ms": 5096.501,
          "norm_abs_end_ms": 331.0
        },
        {
          "ayah": 5,
          "pred_start_s": 22.765,
          "pred_end_s": 26.005,
          "ref_start_s": 22.628,
          "ref_end_s": 26.842,
          "delta_start_ms": 137.061,
          "delta_end_ms": -836.627,
          "abs_start_ms": 137.061,
          "abs_end_ms": 836.627,
          "norm_delta_start_ms": -6.0,
          "norm_delta_end_ms": -979.688,
          "norm_abs_start_ms": 6.0,
          "norm_abs_end_ms": 979.688
        },
        {
          "ayah": 6,
          "pred_start_s": 32.89,
          "pred_end_s": 39.36,
          "ref_start_s": 26.842,
          "ref_end_s": 39.937,
          "delta_start_ms": 6048.373,
          "delta_end_ms": -577.002,
          "abs_start_ms": 6048.373,
          "abs_end_ms": 577.002,
          "norm_delta_start_ms": 5905.313,
          "norm_delta_end_ms": -720.062,
          "norm_abs_start_ms": 5905.313,
          "norm_abs_end_ms": 720.062
        },
        {
          "ayah": 7,
          "pred_start_s": 40.04,
          "pred_end_s": 47.0,
          "ref_start_s": 39.937,
          "ref_end_s": 47.181,
          "delta_start_ms": 102.998,
          "delta_end_ms": -180.94,
          "abs_start_ms": 102.998,
          "abs_end_ms": 180.94,
          "norm_delta_start_ms": -40.062,
          "norm_delta_end_ms": -324.0,
          "norm_abs_start_ms": 40.062,
          "norm_abs_end_ms": 324.0
        },
        {
          "ayah": 8,
          "pred_start_s": 47.33,
          "pred_end_s": 55.4,
          "ref_start_s": 47.181,
          "ref_end_s": 56.175,
          "delta_start_ms": 149.06,
          "delta_end_ms": -775.065,
          "abs_start_ms": 149.06,
          "abs_end_ms": 775.065,
          "norm_delta_start_ms": 6.0,
          "norm_delta_end_ms": -918.125,
          "norm_abs_start_ms": 6.0,
          "norm_abs_end_ms": 918.125
        }
      ]
    }
  },
  "provenance": {
    "engine": {
      "name": "ensemble",
      "model": "ayah-wise",
      "device": "cpu",
      "fallback_used": true,
      "attempted": ["nemo", "whisperx", "mfa"]
    },
    "selected_candidate_engine": "ensemble",
    "candidate_scores": {
      "nemo": 144.92301127512295,
      "mfa": 144.85076379136734
    },
    "pass_trace": [
      "A_audio_normalization",
      "B_ayah_anchors",
      "C_word_candidates",
      "D_candidate_fusion",
      "E_boundary_refinement",
      "F_qc_gates_and_rescue"
    ],
    "supervision_sources": [
      "everyayah:subfolder=Yasser_Ad-Dussary_128kbps:surah=99:scope=full_surah"
    ],
    "segment_source_type": "none"
  },
  "timings_endpoint": "/data/reciters/eya_yasser_ad_dussary_128kbps/surahs/99/timings.json",
  "updated_at": "2026-03-09T19:55:12.748944+00:00"
}
