{
  "schema_version": "v1",
  "audio": {
    "path": "/Users/atlantic/Developer/quran-audio-data/samples/audio/sa3ood_al-shuraym_101.mp3",
    "duration_s": 35.32453514739229,
    "sample_rate": 44100,
    "channels": 2
  },
  "meta": {
    "reciter_id": "sa3ood_al-shuraym",
    "surah": 101,
    "input_mode": "full_surah"
  },
  "engine": {
    "name": "ensemble",
    "model": "ayah-wise",
    "device": "cpu",
    "fallback_used": true
  },
  "ayahs": [
    {
      "surah": 101,
      "ayah": 1,
      "start_s": 2.96575,
      "end_s": 3.6573125,
      "source": "aligned"
    },
    {
      "surah": 101,
      "ayah": 2,
      "start_s": 3.831,
      "end_s": 5.0634375,
      "source": "aligned"
    },
    {
      "surah": 101,
      "ayah": 3,
      "start_s": 5.1761875,
      "end_s": 8.1004375,
      "source": "aligned"
    },
    {
      "surah": 101,
      "ayah": 4,
      "start_s": 8.151,
      "end_s": 12.7568125,
      "source": "aligned"
    },
    {
      "surah": 101,
      "ayah": 5,
      "start_s": 13.0410625,
      "end_s": 16.8555,
      "source": "aligned"
    },
    {
      "surah": 101,
      "ayah": 6,
      "start_s": 17.5516875,
      "end_s": 20.768,
      "source": "aligned"
    },
    {
      "surah": 101,
      "ayah": 7,
      "start_s": 21.097875,
      "end_s": 23.617625,
      "source": "aligned"
    },
    {
      "surah": 101,
      "ayah": 8,
      "start_s": 23.801375,
      "end_s": 26.8443125,
      "source": "aligned"
    },
    {
      "surah": 101,
      "ayah": 9,
      "start_s": 27.0563125,
      "end_s": 29.126125,
      "source": "aligned"
    },
    {
      "surah": 101,
      "ayah": 10,
      "start_s": 29.40725,
      "end_s": 31.7735,
      "source": "aligned"
    },
    {
      "surah": 101,
      "ayah": 11,
      "start_s": 31.96,
      "end_s": 33.9455625,
      "source": "aligned"
    }
  ],
  "words": [
    {
      "surah": 101,
      "ayah": 1,
      "word_index_global": 1,
      "word_index_in_ayah": 1,
      "text_uthmani": "ٱلۡقَارِعَةُ",
      "text_norm": "القارعة",
      "start_s": 2.96575,
      "end_s": 3.6573125,
      "confidence": null,
      "alignment_origin": "native",
      "match_score": 100.0,
      "engine_candidate": "nemo"
    },
    {
      "surah": 101,
      "ayah": 2,
      "word_index_global": 2,
      "word_index_in_ayah": 1,
      "text_uthmani": "مَا",
      "text_norm": "ما",
      "start_s": 3.831,
      "end_s": 3.851,
      "confidence": null,
      "alignment_origin": "native",
      "match_score": 100.0,
      "engine_candidate": "nemo"
    },
    {
      "surah": 101,
      "ayah": 2,
      "word_index_global": 3,
      "word_index_in_ayah": 2,
      "text_uthmani": "ٱلۡقَارِعَةُ",
      "text_norm": "القارعة",
      "start_s": 4.178375,
      "end_s": 5.0634375,
      "confidence": null,
      "alignment_origin": "native",
      "match_score": 100.0,
      "engine_candidate": "nemo"
    },
    {
      "surah": 101,
      "ayah": 3,
      "word_index_global": 4,
      "word_index_in_ayah": 1,
      "text_uthmani": "وَمَاۤ",
      "text_norm": "وما",
      "start_s": 5.1761875,
      "end_s": 5.2569375,
      "confidence": null,
      "alignment_origin": "native",
      "match_score": 100.0,
      "engine_candidate": "nemo"
    },
    {
      "surah": 101,
      "ayah": 3,
      "word_index_global": 5,
      "word_index_in_ayah": 2,
      "text_uthmani": "أَدۡرَىٰكَ",
      "text_norm": "ادريك",
      "start_s": 6.016125,
      "end_s": 6.715,
      "confidence": null,
      "alignment_origin": "native",
      "match_score": 100.0,
      "engine_candidate": "nemo"
    },
    {
      "surah": 101,
      "ayah": 3,
      "word_index_global": 6,
      "word_index_in_ayah": 3,
      "text_uthmani": "مَا",
      "text_norm": "ما",
      "start_s": 6.8960625,
      "end_s": 6.9160625,
      "confidence": null,
      "alignment_origin": "native",
      "match_score": 100.0,
      "engine_candidate": "nemo"
    },
    {
      "surah": 101,
      "ayah": 3,
      "word_index_global": 7,
      "word_index_in_ayah": 4,
      "text_uthmani": "ٱلۡقَارِعَةُ",
      "text_norm": "القارعة",
      "start_s": 7.1440625,
      "end_s": 8.1004375,
      "confidence": null,
      "alignment_origin": "native",
      "match_score": 100.0,
      "engine_candidate": "nemo"
    },
    {
      "surah": 101,
      "ayah": 4,
      "word_index_global": 8,
      "word_index_in_ayah": 1,
      "text_uthmani": "یَوۡمَ",
      "text_norm": "يوم",
      "start_s": 8.151,
      "end_s": 8.2506875,
      "confidence": null,
      "alignment_origin": "native",
      "match_score": 100.0,
      "engine_candidate": "nemo"
    },
    {
      "surah": 101,
      "ayah": 4,
      "word_index_global": 9,
      "word_index_in_ayah": 2,
      "text_uthmani": "یَكُونُ",
      "text_norm": "يكون",
      "start_s": 8.9380625,
      "end_s": 8.958062499999999,
      "confidence": null,
      "alignment_origin": "native",
      "match_score": 100.0,
      "engine_candidate": "nemo"
    },
    {
      "surah": 101,
      "ayah": 4,
      "word_index_global": 10,
      "word_index_in_ayah": 3,
      "text_uthmani": "ٱلنَّاسُ",
      "text_norm": "الناس",
      "start_s": 9.6750625,
      "end_s": 9.7399375,
      "confidence": null,
      "alignment_origin": "native",
      "match_score": 100.0,
      "engine_candidate": "nemo"
    },
    {
      "surah": 101,
      "ayah": 4,
      "word_index_global": 11,
      "word_index_in_ayah": 4,
      "text_uthmani": "كَٱلۡفَرَاشِ",
      "text_norm": "كالفراش",
      "start_s": 10.4406875,
      "end_s": 11.549,
      "confidence": null,
      "alignment_origin": "native",
      "match_score": 100.0,
      "engine_candidate": "nemo"
    },
    {
      "surah": 101,
      "ayah": 4,
      "word_index_global": 12,
      "word_index_in_ayah": 5,
      "text_uthmani": "ٱلۡمَبۡثُوثِ",
      "text_norm": "المبثوث",
      "start_s": 11.549,
      "end_s": 12.7568125,
      "confidence": null,
      "alignment_origin": "native",
      "match_score": 100.0,
      "engine_candidate": "nemo"
    },
    {
      "surah": 101,
      "ayah": 5,
      "word_index_global": 13,
      "word_index_in_ayah": 1,
      "text_uthmani": "وَتَكُونُ",
      "text_norm": "وتكون",
      "start_s": 13.0410625,
      "end_s": 13.6180625,
      "confidence": null,
      "alignment_origin": "native",
      "match_score": 100.0,
      "engine_candidate": "nemo"
    },
    {
      "surah": 101,
      "ayah": 5,
      "word_index_global": 14,
      "word_index_in_ayah": 2,
      "text_uthmani": "ٱلۡجِبَالُ",
      "text_norm": "الجبال",
      "start_s": 14.218875,
      "end_s": 14.8378125,
      "confidence": null,
      "alignment_origin": "native",
      "match_score": 100.0,
      "engine_candidate": "nemo"
    },
    {
      "surah": 101,
      "ayah": 5,
      "word_index_global": 15,
      "word_index_in_ayah": 3,
      "text_uthmani": "كَٱلۡعِهۡنِ",
      "text_norm": "كالعهن",
      "start_s": 14.885125,
      "end_s": 15.6333125,
      "confidence": null,
      "alignment_origin": "native",
      "match_score": 100.0,
      "engine_candidate": "nemo"
    },
    {
      "surah": 101,
      "ayah": 5,
      "word_index_global": 16,
      "word_index_in_ayah": 4,
      "text_uthmani": "ٱلۡمَنفُوشِ",
      "text_norm": "المنفوش",
      "start_s": 15.8113125,
      "end_s": 16.8555,
      "confidence": null,
      "alignment_origin": "native",
      "match_score": 100.0,
      "engine_candidate": "nemo"
    },
    {
      "surah": 101,
      "ayah": 6,
      "word_index_global": 17,
      "word_index_in_ayah": 1,
      "text_uthmani": "فَأَمَّا",
      "text_norm": "فاما",
      "start_s": 17.5516875,
      "end_s": 17.969375,
      "confidence": null,
      "alignment_origin": "native",
      "match_score": 100.0,
      "engine_candidate": "nemo"
    },
    {
      "surah": 101,
      "ayah": 6,
      "word_index_global": 18,
      "word_index_in_ayah": 2,
      "text_uthmani": "مَن",
      "text_norm": "من",
      "start_s": 18.4195625,
      "end_s": 18.4395625,
      "confidence": null,
      "alignment_origin": "native",
      "match_score": 100.0,
      "engine_candidate": "nemo"
    },
    {
      "surah": 101,
      "ayah": 6,
      "word_index_global": 19,
      "word_index_in_ayah": 3,
      "text_uthmani": "ثَقُلَتۡ",
      "text_norm": "ثقلت",
      "start_s": 19.0794375,
      "end_s": 19.7493125,
      "confidence": null,
      "alignment_origin": "native",
      "match_score": 100.0,
      "engine_candidate": "nemo"
    },
    {
      "surah": 101,
      "ayah": 6,
      "word_index_global": 20,
      "word_index_in_ayah": 4,
      "text_uthmani": "مَوَ",
      "text_norm": "مو",
      "start_s": 19.7493125,
      "end_s": 20.1893125,
      "confidence": null,
      "alignment_origin": "native",
      "match_score": 100.0,
      "engine_candidate": "nemo"
    },
    {
      "surah": 101,
      "ayah": 6,
      "word_index_global": 21,
      "word_index_in_ayah": 5,
      "text_uthmani": "ٰزِینُهُۥ",
      "text_norm": "زينه",
      "start_s": 20.257625,
      "end_s": 20.768,
      "confidence": null,
      "alignment_origin": "native",
      "match_score": 100.0,
      "engine_candidate": "nemo"
    },
    {
      "surah": 101,
      "ayah": 7,
      "word_index_global": 22,
      "word_index_in_ayah": 1,
      "text_uthmani": "فَهُوَ",
      "text_norm": "فهو",
      "start_s": 21.097875,
      "end_s": 21.117874999999998,
      "confidence": null,
      "alignment_origin": "native",
      "match_score": 100.0,
      "engine_candidate": "nemo"
    },
    {
      "surah": 101,
      "ayah": 7,
      "word_index_global": 23,
      "word_index_in_ayah": 2,
      "text_uthmani": "فِی",
      "text_norm": "في",
      "start_s": 21.58725,
      "end_s": 21.60725,
      "confidence": null,
      "alignment_origin": "native",
      "match_score": 100.0,
      "engine_candidate": "nemo"
    },
    {
      "surah": 101,
      "ayah": 7,
      "word_index_global": 24,
      "word_index_in_ayah": 3,
      "text_uthmani": "عِیشَةࣲ",
      "text_norm": "عيشةࣲ",
      "start_s": 21.9073125,
      "end_s": 22.5868125,
      "confidence": null,
      "alignment_origin": "native",
      "match_score": 100.0,
      "engine_candidate": "nemo"
    },
    {
      "surah": 101,
      "ayah": 7,
      "word_index_global": 25,
      "word_index_in_ayah": 4,
      "text_uthmani": "رَّاضِیَةࣲ",
      "text_norm": "راضيةࣲ",
      "start_s": 22.602625,
      "end_s": 23.617625,
      "confidence": null,
      "alignment_origin": "native",
      "match_score": 100.0,
      "engine_candidate": "nemo"
    },
    {
      "surah": 101,
      "ayah": 8,
      "word_index_global": 26,
      "word_index_in_ayah": 1,
      "text_uthmani": "وَأَمَّا",
      "text_norm": "واما",
      "start_s": 23.801375,
      "end_s": 24.309,
      "confidence": null,
      "alignment_origin": "native",
      "match_score": 100.0,
      "engine_candidate": "nemo"
    },
    {
      "surah": 101,
      "ayah": 8,
      "word_index_global": 27,
      "word_index_in_ayah": 2,
      "text_uthmani": "مَنۡ",
      "text_norm": "من",
      "start_s": 24.86175,
      "end_s": 24.88175,
      "confidence": null,
      "alignment_origin": "native",
      "match_score": 100.0,
      "engine_candidate": "nemo"
    },
    {
      "surah": 101,
      "ayah": 8,
      "word_index_global": 28,
      "word_index_in_ayah": 3,
      "text_uthmani": "خَفَّتۡ",
      "text_norm": "خفت",
      "start_s": 25.1668125,
      "end_s": 25.500375,
      "confidence": null,
      "alignment_origin": "native",
      "match_score": 100.0,
      "engine_candidate": "nemo"
    },
    {
      "surah": 101,
      "ayah": 8,
      "word_index_global": 29,
      "word_index_in_ayah": 4,
      "text_uthmani": "مَوَ",
      "text_norm": "مو",
      "start_s": 25.7200625,
      "end_s": 26.2758125,
      "confidence": null,
      "alignment_origin": "native",
      "match_score": 100.0,
      "engine_candidate": "nemo"
    },
    {
      "surah": 101,
      "ayah": 8,
      "word_index_global": 30,
      "word_index_in_ayah": 5,
      "text_uthmani": "ٰزِینُهُۥ",
      "text_norm": "زينه",
      "start_s": 26.2758125,
      "end_s": 26.8443125,
      "confidence": null,
      "alignment_origin": "native",
      "match_score": 100.0,
      "engine_candidate": "nemo"
    },
    {
      "surah": 101,
      "ayah": 9,
      "word_index_global": 31,
      "word_index_in_ayah": 1,
      "text_uthmani": "فَأُمُّهُۥ",
      "text_norm": "فامه",
      "start_s": 27.0563125,
      "end_s": 27.9685,
      "confidence": null,
      "alignment_origin": "native",
      "match_score": 100.0,
      "engine_candidate": "nemo"
    },
    {
      "surah": 101,
      "ayah": 9,
      "word_index_global": 32,
      "word_index_in_ayah": 2,
      "text_uthmani": "هَاوِیَةࣱ",
      "text_norm": "هاويةࣱ",
      "start_s": 28.2655,
      "end_s": 29.126125,
      "confidence": null,
      "alignment_origin": "native",
      "match_score": 100.0,
      "engine_candidate": "nemo"
    },
    {
      "surah": 101,
      "ayah": 10,
      "word_index_global": 33,
      "word_index_in_ayah": 1,
      "text_uthmani": "وَمَاۤ",
      "text_norm": "وما",
      "start_s": 29.40725,
      "end_s": 29.719125,
      "confidence": null,
      "alignment_origin": "native",
      "match_score": 100.0,
      "engine_candidate": "nemo"
    },
    {
      "surah": 101,
      "ayah": 10,
      "word_index_global": 34,
      "word_index_in_ayah": 2,
      "text_uthmani": "أَدۡرَىٰكَ",
      "text_norm": "ادريك",
      "start_s": 30.035875,
      "end_s": 30.7209375,
      "confidence": null,
      "alignment_origin": "native",
      "match_score": 100.0,
      "engine_candidate": "nemo"
    },
    {
      "surah": 101,
      "ayah": 10,
      "word_index_global": 35,
      "word_index_in_ayah": 3,
      "text_uthmani": "مَا",
      "text_norm": "ما",
      "start_s": 30.959875,
      "end_s": 30.979875,
      "confidence": null,
      "alignment_origin": "native",
      "match_score": 100.0,
      "engine_candidate": "nemo"
    },
    {
      "surah": 101,
      "ayah": 10,
      "word_index_global": 36,
      "word_index_in_ayah": 4,
      "text_uthmani": "هِیَهۡ",
      "text_norm": "هيه",
      "start_s": 31.2656875,
      "end_s": 31.7735,
      "confidence": null,
      "alignment_origin": "native",
      "match_score": 100.0,
      "engine_candidate": "nemo"
    },
    {
      "surah": 101,
      "ayah": 11,
      "word_index_global": 37,
      "word_index_in_ayah": 1,
      "text_uthmani": "نَارٌ",
      "text_norm": "نار",
      "start_s": 31.96,
      "end_s": 32.558,
      "confidence": null,
      "alignment_origin": "native",
      "match_score": 100.0,
      "engine_candidate": "nemo"
    },
    {
      "surah": 101,
      "ayah": 11,
      "word_index_global": 38,
      "word_index_in_ayah": 2,
      "text_uthmani": "حَامِیَةُۢ",
      "text_norm": "حامية",
      "start_s": 32.8969375,
      "end_s": 33.9455625,
      "confidence": null,
      "alignment_origin": "native",
      "match_score": 100.0,
      "engine_candidate": "nemo"
    }
  ],
  "qc": {
    "coverage": 1.0,
    "monotonic": true,
    "duration_match": true,
    "warnings": [
      "boundary_refinement_applied"
    ],
    "zero_or_negative_ratio": 0.0,
    "median_confidence": null,
    "interpolated_ratio": 0.0,
    "lexical_match_ratio": 1.0,
    "speech_end_delta_ratio": 0.0033381240740262105,
    "quantization_step_ms": 336.2499999999997,
    "engine_candidate_scores": {
      "nemo": 164.98910075703554,
      "mfa": 164.96656536891686
    }
  }
}